Metadata-Version: 1.0
Name: ggb-probability
Version: 0.1
Summary: Distributions
Home-page: UNKNOWN
Author: Tushar Mehta
Author-email: tusharmehta0810@gmail.com
License: UNKNOWN
Platform: UNKNOWN
